fauxtp/__init__.py
fauxtp/messaging.py
fauxtp/py.typed
fauxtp/registry.py
fauxtp/supervisor.py
fauxtp/type_utils.py
fauxtp/actor/__init__.py
fauxtp/actor/base.py
fauxtp/actor/genserver.py
fauxtp/actor/task.py
fauxtp/fauxstorage/__init__.py
fauxtp/fauxstorage/dict.py
fauxtp/fauxstorage/generic.py
fauxtp/fauxstorage/rpds.py
fauxtp/primitives/__init__.py
fauxtp/primitives/mailbox.py
fauxtp/primitives/pattern.py
fauxtp/primitives/pid.py
fauxtp/testing/__init__.py
fauxtp/testing/helpers.py
fauxtp-0.3.1.dist-info/METADATA
fauxtp-0.3.1.dist-info/WHEEL
fauxtp-0.3.1.dist-info/licenses/LICENSE
fauxtp-0.3.1.dist-info/RECORD
