Metadata-Version: 2.4
Name: fauxtp
Version: 0.3.1
Summary: Erlang/OTP primitives for Python.
Project-URL: Documentation, https://fizzai.github.io/fauxtp/
Project-URL: Repository, https://github.com/fizzAI/fauxtp
Author-email: fizzAI <fizzarolli@riseup.net>
License-Expression: BSD-2-Clause
License-File: LICENSE
Requires-Python: >=3.11
Requires-Dist: anyio>=4.12.1
Provides-Extra: dev
Requires-Dist: pytest-asyncio>=0.23.0; extra == 'dev'
Requires-Dist: pytest-cov>=4.1.0; extra == 'dev'
Requires-Dist: pytest>=8.0.0; extra == 'dev'
Provides-Extra: docs
Requires-Dist: jupyter-book>=2.1.0; extra == 'docs'
Requires-Dist: mkdocs-material>=9.7.1; extra == 'docs'
Requires-Dist: mkdocs>=1.6.1; extra == 'docs'
Requires-Dist: mkdocstrings[python]>=1.0.0; extra == 'docs'
Provides-Extra: rpds
Requires-Dist: rpds-py>=0.30.0; extra == 'rpds'
